genomediff/__init__.py
genomediff/parser.py
genomediff/records.py
genomediff2-0.3.3.dist-info/LICENSE
genomediff2-0.3.3.dist-info/METADATA
genomediff2-0.3.3.dist-info/WHEEL
genomediff2-0.3.3.dist-info/top_level.txt
genomediff2-0.3.3.dist-info/RECORD
