Metadata-Version: 2.1
Name: genomediff2
Version: 0.3.3
Summary: GenomeDiff (*.gd) file reader
Home-page: https://github.com/biosustain/genomediff-python.git
Author: Lars Schoening
Author-email: lays@biosustain.dtu.dk
License: MIT
Classifier: Development Status :: 3 - Alpha
Classifier: Environment :: Other Environment
Classifier: Intended Audience :: Science/Research
Classifier: License :: OSI Approved :: MIT License
Classifier: Operating System :: OS Independent
Classifier: Programming Language :: Python :: 3
Classifier: Topic :: Scientific/Engineering :: Bio-Informatics
License-File: LICENSE
